{"__symbolic":"module","version":1,"metadata":{"DYNAMIC_TYPE":{"__symbolic":"new","expression":{"__symbolic":"reference","name":"BuiltinType"},"arguments":[null]},"BOOL_TYPE":{"__symbolic":"new","expression":{"__symbolic":"reference","name":"BuiltinType"},"arguments":[null]},"INT_TYPE":{"__symbolic":"new","expression":{"__symbolic":"reference","name":"BuiltinType"},"arguments":[null]},"NUMBER_TYPE":{"__symbolic":"new","expression":{"__symbolic":"reference","name":"BuiltinType"},"arguments":[null]},"STRING_TYPE":{"__symbolic":"new","expression":{"__symbolic":"reference","name":"BuiltinType"},"arguments":[null]},"FUNCTION_TYPE":{"__symbolic":"new","expression":{"__symbolic":"reference","name":"BuiltinType"},"arguments":[null]},"THIS_EXPR":{"__symbolic":"new","expression":{"__symbolic":"reference","name":"ReadVarExpr"},"arguments":[null]},"SUPER_EXPR":{"__symbolic":"new","expression":{"__symbolic":"reference","name":"ReadVarExpr"},"arguments":[null]},"CATCH_ERROR_VAR":{"__symbolic":"new","expression":{"__symbolic":"reference","name":"ReadVarExpr"},"arguments":[null]},"CATCH_STACK_VAR":{"__symbolic":"new","expression":{"__symbolic":"reference","name":"ReadVarExpr"},"arguments":[null]},"NULL_EXPR":{"__symbolic":"new","expression":{"__symbolic":"reference","name":"LiteralExpr"},"arguments":[null,null]}}}